[{"name":"Janis","surname":"Berzs","gender":"male","email":"janis@berzs.lv","birth_year":"1997","picture_path":"6d\/2a\/6d2aded4adead3c5e8ef13ea6d5355d6.jpg"},{"name":"Ansis","surname":"Kocins","gender":"male","email":"ansis@kocins.lv","birth_year":"1999","picture_path":"43\/2f\/432fc0b91d8402aaf98edf61fcfdf661.jpg"},{"name":"Valdis","surname":"Bertrups","gender":"male","email":"valdis@bertrups.lv","birth_year":"1985","picture_path":"83\/f5\/83f5a44a888695e034af2d5566dd94db.jpg"},{"name":"Karlis","surname":"Kocins","gender":"male","email":"karlis@kocins.lv","birth_year":"1992","picture_path":"ee\/db\/eedb99f7c15810dd7136a8562c1b3316.jpg"},{"name":"Ansis","surname":"Priede","gender":"male","email":"ansis@priede.lv","birth_year":"1981","picture_path":"43\/0b\/430b29c1c738ebcadbb4324de13a3f25.jpg"},{"name":"Maris","surname":"Olte","gender":"male","email":"maris@olte.lv","birth_year":"1973","picture_path":"2e\/48\/2e48ae20ca08239fec06a598a8c37e6b.jpg"},{"name":"Adolfs","surname":"Merce","gender":"male","email":"adolfs@merce.lv","birth_year":"1997","picture_path":"3b\/ee\/3beeae9ec494012246b9059e14933167.jpg"},{"name":"Janis","surname":"Felzens","gender":"male","email":"janis@felzens.lv","birth_year":"1987","picture_path":"21\/50\/21508623f6936e95b041b8338d812e8a.jpg"}]